{
  "primary": "#333333",
  "secondary": "#FFFFFF",
  "accent": "#00A99D",
  "background": "#FFFFFF",
  "text": "#000000",
  "textSecondary": "#333333",
  "border": "#333333",
  "success": "#0F4C5C",
  "warning": "#FFA500",
  "error": "#FF0000",
  "info": "#1E90FF",
  "colorTheory": {
    "description": "This palette combines a neutral base with a pop of color for visual interest and accessibility.",
    "mood": "Professional and modern with a touch of creativity.",
    "accessibility": "The high contrast between text and background colors ensures readability.",
    "colorRelationships": "The primary and secondary colors create a balanced and harmonious foundation, while the accent color adds vibrancy."
  },
  "allColors": [
    "#000000",
    "#00A99D",
    "#333333",
    "#FFFFFF"
  ],
  "dropdownBackground": "#333333"
}